spikedata/__init__.py
spikedata/_version.py
spikedata/spikedata.py
spikedata-0.2.1.dist-info/METADATA
spikedata-0.2.1.dist-info/WHEEL
spikedata-0.2.1.dist-info/licenses/LICENSE
spikedata-0.2.1.dist-info/RECORD
