Metadata-Version: 2.4
Name: spikedata
Version: 0.2.1
Summary: Toolkit for processing spiking neural time series
Project-URL: Homepage, https://github.com/braingeneers/SpikeData
Author-email: UCSC Braingeneers <ucscgi@ucsc.edu>
Maintainer-email: Alex <atspaeth@ucsc.edu>, Lon <lblauvel@ucsc.edu>
License-File: LICENSE
Classifier: Development Status :: 3 - Alpha
Classifier: Intended Audience :: Developers
Classifier: Intended Audience :: Science/Research
Classifier: License :: OSI Approved :: MIT License
Classifier: Operating System :: OS Independent
Classifier: Programming Language :: Python
Classifier: Programming Language :: Python :: 3
Classifier: Programming Language :: Python :: 3 :: Only
Classifier: Programming Language :: Python :: 3.10
Classifier: Programming Language :: Python :: 3.11
Classifier: Topic :: Scientific/Engineering
Classifier: Typing :: Typed
Requires-Python: >=3.10
Requires-Dist: numpy
Requires-Dist: scipy>=1.10.0
Provides-Extra: all
Requires-Dist: powerlaw>=1.5; extra == 'all'
